[
    {
        "Brand Name": [
            "Watersino"
        ],
        "Certificate": [
            "CUPC"
        ],
        "Color": [
            "Packing in one carton box with foam"
        ],
        "Cover": [
            "Smooth"
        ],
        "Drainage Pattern": [
            "P-Trap, S-Trap"
        ],
        "Feature": [
            "Dual-Flush"
        ],
        "Flush": [
            "Bathroom Siphonic One-Piece toilet"
        ],
        "HighPrice": [
            "160"
        ],
        "Installation Type": [
            "Floor Mounted"
        ],
        "LowPrice": [
            "1"
        ],
        "Material": [
            "Ceramic"
        ],
        "Model Number": [
            "JD-541"
        ],
        "Name": [
            "One Piece Toilet CUPC Elegant Dual Flushing European Toilet"
        ],
        "Place of Origin": [
            "Guangdong, China (Mainland)"
        ],
        "PriceCurrency": [
            "US $"
        ],
        "Size": [
            "Washdown"
        ],
        "Structure": [
            "One Piece"
        ]
    }
]