[
    {
        "Brand Name": [
            "Meizhi"
        ],
        "Certificate": [
            "types of toilet bowl"
        ],
        "Color": [
            "480*370*400mm"
        ],
        "Cover": [
            "nomal one"
        ],
        "Drainage Pattern": [
            "P-Trap"
        ],
        "Feature": [
            "Dual-Flush"
        ],
        "Flush": [
            "simple packing or carton"
        ],
        "HighPrice": [
            "16"
        ],
        "Installation Type": [
            "Floor Mounted"
        ],
        "LowPrice": [
            "13"
        ],
        "Material": [
            "Ceramic"
        ],
        "Model Number": [
            "M-8537"
        ],
        "Name": [
            "Bathroom ceramic small p-trap types of toilet bowl"
        ],
        "Place of Origin": [
            "Guangdong, China (Mainland)"
        ],
        "PriceCurrency": [
            "US $"
        ],
        "Size": [
            "shining"
        ],
        "Structure": [
            "One Piece"
        ]
    }
]