[
    {
        "Brand Name": [
            "Haopeng/Kenisi/OEM"
        ],
        "Certificate": [
            "Slow Down Seat Cover/Dual Flushing Fitting"
        ],
        "Color": [
            "700*385*760mm"
        ],
        "Cover": [
            "yes"
        ],
        "Drainage Pattern": [
            "P-Trap, S-Trap"
        ],
        "Feature": [
            "Dual-Flush"
        ],
        "Flush": [
            "Grade A"
        ],
        "HighPrice": [
            "55"
        ],
        "Installation Type": [
            "Floor Mounted"
        ],
        "LowPrice": [
            "1"
        ],
        "Material": [
            "Ceramic, ceramic"
        ],
        "Model Number": [
            "A-2407"
        ],
        "Name": [
            "Sanitary Ware Bathroom Porcelain square Washdown One Piece Toilets"
        ],
        "Place of Origin": [
            "Guangdong, China (Mainland)"
        ],
        "PriceCurrency": [
            "US $"
        ],
        "Size": [
            "180mm"
        ],
        "Structure": [
            "One Piece"
        ]
    }
]