[
    {
        "Brand Name": [
            "JAFZA"
        ],
        "Color": [
            "toilet"
        ],
        "Cover": [
            "180MM"
        ],
        "Drainage Pattern": [
            "P-Trap, S-Trap"
        ],
        "Feature": [
            "Dual-Flush"
        ],
        "HighPrice": [
            "61"
        ],
        "Installation Type": [
            "Floor Mounted"
        ],
        "LowPrice": [
            "56"
        ],
        "Material": [
            "Ceramic"
        ],
        "Model Number": [
            "1720"
        ],
        "Name": [
            "1720 Brand new one piece sanitary toilet,ceramic one pc toilet,one piece toilet flush down"
        ],
        "Place of Origin": [
            "Guangdong, China (Mainland)"
        ],
        "PriceCurrency": [
            "US $"
        ],
        "Size": [
            "700*390*740MM"
        ],
        "Structure": [
            "One Piece"
        ]
    }
]