[
    {
        "Color": [
            "Stainless Steel 10-Slot Skirted Knife Holder with White Polyethylene Top - 23&quot;L x 2&quot;D x 12&quot;H"
        ],
        "Features": [
            "Rectangular</td>\n\t\t\t\t\t\t\t\t</tr>\n\t\t\t\t\t\t\t\t<tr>\n\t\t\t\t\t\t\t\t\t<th>Length</th>\n\t\t\t\t\t\t\t\t\t<td>23\"</td>\n\t\t\t\t\t\t\t\t</tr>\n\t\t\t\t\t\t\t\t<tr>\n\t\t\t\t\t\t\t\t\t<th class=\"background\">Depth</th>\n\t\t\t\t\t\t\t\t\t<td class=\"background\">2\"</td>\n\t\t\t\t\t\t\t\t</tr>\n\t\t\t\t\t\t\t\t<tr>\n\t\t\t\t\t\t\t\t\t<th>Height</th>\n\t\t\t\t\t\t\t\t\t<td>12\"</td>\n\t\t\t\t\t\t\t\t</tr>\n\t\t\t\t\t\t\t\t<tr>\n\t\t\t\t\t\t\t\t\t<th class=\"background\">Accommodates</th>\n\t\t\t\t\t\t\t\t\t<td class=\"background\">10 Knives"
        ],
        "Material": [
            "Plastic Teapots"
        ],
        "Price": [
            "55.09"
        ],
        "VPN": [
            "POLY12X23.REG"
        ]
    }
]