[
    {
        "Color": [
            "San Jamar Grey Plastic Saf-T-Knife\u2122 Junior Station - 8 1/2W x 4D"
        ],
        "Features": [
            "8.3\"</td>\n\t\t\t\t\t\t\t\t</tr>\n\t\t\t\t\t\t\t\t<tr>\n\t\t\t\t\t\t\t\t\t<th class=\"background\">Depth</th>\n\t\t\t\t\t\t\t\t\t<td class=\"background\">4\"</td>\n\t\t\t\t\t\t\t\t</tr>\n\t\t\t\t\t\t\t\t<tr>\n\t\t\t\t\t\t\t\t\t<th>Height</th>\n\t\t\t\t\t\t\t\t\t<td>14.5\"</td>\n\t\t\t\t\t\t\t\t</tr>\n\t\t\t\t\t\t\t\t<tr>\n\t\t\t\t\t\t\t\t\t<th class=\"background\">Certifications</th>\n\t\t\t\t\t\t\t\t\t<td class=\"background\">NSF</td>\n\t\t\t\t\t\t\t\t</tr>\n\t\t\t\t\t\t\t\t<tr>\n\t\t\t\t\t\t\t\t\t<th>Features</th>\n\t\t\t\t\t\t\t\t\t<td>Dishwasher Safe"
        ],
        "Material": [
            "Plastic Teapots"
        ],
        "Price": [
            "37.39"
        ],
        "VPN": [
            "STK1006"
        ]
    }
]