[
    {
        "Brand Name": [
            "CIQ,CE / EU"
        ],
        "Certification": [
            "Gift Box"
        ],
        "Feature": [
            "141130"
        ],
        "Knife Type": [
            "WGP"
        ],
        "Material": [
            "Stocked,Eco-Friendly"
        ],
        "Model Number": [
            "Metal"
        ],
        "Name": [
            "Creative gift Gift Spoon Fork Chopsticks Cutlery Set Travel Camping Picnic Necessity Kit Portable Tableware 2pcs/set  HK080115#"
        ],
        "Type": [
            "Frost"
        ],
        "Use for": [
            "Animal"
        ]
    }
]