[
    {
        "Certification": [
            "Eco-Friendly"
        ],
        "Knife Type": [
            "Larcolais"
        ],
        "Model Number": [
            "Ceramic"
        ],
        "Name": [
            "Home Kitchen Dining Bar Ceramic Knife and Accessories Set Paring Fruit Utility Chef 3&quot; 4&quot; 5&quot; 6&quot; inch with Peeler Acrylic Holder"
        ],
        "Price Discount": [
            "\n\t\tif(!window.runParams) {\n\t\twindow.runParams = {};\n\t\t}\n\t\twindow.runParams.minPrice=\"32.46\";\n\t\twindow.runParams.maxPrice=\"32.46\";\n\t\twindow.runParams.baseCurrencyCode=\"USD\";\n\t\twindow.runParams.baseCurrencySymbol=\"US $\";\n\t\twindow.runParams.baseSymbolFront=true;\n\t\twindow.runParams.isGroupJoin=\"\";\n        window.runParams.abMzcVersion=\"\";\n        window.runParams.isCoinPreSale=\"\";\n        window.runParams.applyScene=\"\";\n        window.runParams.atLeastCoinEnough = \"\";\n        window.runParams.miniCoinNeed = \"\";\n        window.runParams.isOpenBanner=\"\";\n\t\t\t\twindow.runParams.pageSizeID=\"\";\n\t\twindow.runParams.pageSizeType=\"\";\n\t\twindow.runParams.hasSizeInfo=false;\n\t\twindow.runParams.pageSizeTemplate='';\n\t\twindow.runParams.pageSizeBuyerData='';\n\t\t\t\t    window.runParams.pageSizeSellerData={};\n        \n                    window.runParams.title={};\n        \n        window.runParams.isNewSizeInfo=false;\n\t\twindow.runParams.offline=true;\n\t\twindow.runParams.csrfToken=\"1eg1ayerz59g8\";\n\t\twindow.runParams.productId=\"1904533610\";\n        window.runParams.serverTime=\"1523793493504\";\n\t\twindow.runParams.userCountry=\"IT\";\n\t\twindow.runParams.userCountryName=\"Italy\";\n\t\twindow.runParams.regionCountryName=\"Italy\";\n\t\twindow.runParams.regionProvinceName=\"\";\n\t\twindow.runParams.regionCityName=\"\";\n        window.runParams.sessionId=\"4aff379dcff04dd7a5c847c3312e7fda\";\n\t\t\t\twindow.runParams.currencyCode=\"USD\";\n\t\twindow.runParams.currencySymbol=\"US $\";\n\t\twindow.runParams.currencyRate=\"1.0\";\n\t\twindow.runParams.symbolFront=true;\n\t\twindow.runParams.currencyTransaction=true;\n\t\t\t\t\n\t\twindow.runParams.hasMobileDiscount=\"false\";\n\twindow.runParams.mobileDiscountPrice=\"\";\n\n\t\n\t\t\twindow.runParams.totalAvailQuantity=6894;\n\twindow.runParams.memberPrice=\"\";\n\twindow.runParams.memberPriceActivity=\"\";\n\twindow.runParams.quantityLimit={\n\t\tisPurchaseLimit: \"\",\n\t\t\t\tunit: 'Sets',\n\t\t\t\tquantityNum: '6894 ',\n\t\tavailQuantityForCustomer: '6894'\n\t};\n\n\t\t\twindow.runParams.warrantyServiceJson=[];\n\t\t\t\twindow.runParams.forcePromiseWarrantyJson={};\n\t\twindow.runParams.hasOverseaWarehouse=\"false\";\n\n\tvar skuProducts=[{\"skuAttr\":\"14:173;200007763:201336100\",\"skuPropIds\":\"173,201336100\",\"skuVal\":{\"availQuantity\":988,\"inventory\":999,\"isActivity\":false,\"skuCalPrice\":\"32.46\",\"skuMultiCurrencyCalPrice\":\"32.46\",\"skuMultiCurrencyDisplayPrice\":\"32.46\"}},{\"skuAttr\":\"14:173;200007763:201336103\",\"skuPropIds\":\"173,201336103\",\"skuVal\":{\"availQuantity\":0,\"inventory\":0,\"isActivity\":false,\"skuCalPrice\":\"32.46\",\"skuMultiCurrencyCalPrice\":\"32.46\",\"skuMultiCurrencyDisplayPrice\":\"32.46\"}},{\"skuAttr\":\"14:175;200007763:201336100\",\"skuPropIds\":\"175,201336100\",\"skuVal\":{\"availQuantity\":969,\"inventory\":999,\"isActivity\":false,\"skuCalPrice\":\"32.46\",\"skuMultiCurrencyCalPrice\":\"32.46\",\"skuMultiCurrencyDisplayPrice\":\"32.46\"}},{\"skuAttr\":\"14:175;200007763:201336103\",\"skuPropIds\":\"175,201336103\",\"skuVal\":{\"availQuantity\":54,\"inventory\":90,\"isActivity\":false,\"skuCalPrice\":\"32.46\",\"skuMultiCurrencyCalPrice\":\"32.46\",\"skuMultiCurrencyDisplayPrice\":\"32.46\"}},{\"skuAttr\":\"14:193;200007763:201336100\",\"skuPropIds\":\"193,201336100\",\"skuVal\":{\"availQuantity\":938,\"inventory\":999,\"isActivity\":false,\"skuCalPrice\":\"32.46\",\"skuMultiCurrencyCalPrice\":\"32.46\",\"skuMultiCurrencyDisplayPrice\":\"32.46\"}},{\"skuAttr\":\"14:193;200007763:201336103\",\"skuPropIds\":\"193,201336103\",\"skuVal\":{\"availQuantity\":51,\"inventory\":134,\"isActivity\":false,\"skuCalPrice\":\"32.46\",\"skuMultiCurrencyCalPrice\":\"32.46\",\"skuMultiCurrencyDisplayPrice\":\"32.46\"}},{\"skuAttr\":\"14:200003699;200007763:201336100\",\"skuPropIds\":\"200003699,201336100\",\"skuVal\":{\"availQuantity\":912,\"inventory\":999,\"isActivity\":false,\"skuCalPrice\":\"32.46\",\"skuMultiCurrencyCalPrice\":\"32.46\",\"skuMultiCurrencyDisplayPrice\":\"32.46\"}},{\"skuAttr\":\"14:200003699;200007763:201336103\",\"skuPropIds\":\"200003699,201336103\",\"skuVal\":{\"availQuantity\":31,\"inventory\":175,\"isActivity\":false,\"skuCalPrice\":\"32.46\",\"skuMultiCurrencyCalPrice\":\"32.46\",\"skuMultiCurrencyDisplayPrice\":\"32.46\"}},{\"skuAttr\":\"14:200005536;200007763:201336100\",\"skuPropIds\":\"200005536,201336100\",\"skuVal\":{\"availQuantity\":980,\"inventory\":999,\"isActivity\":false,\"skuCalPrice\":\"32.46\",\"skuMultiCurrencyCalPrice\":\"32.46\",\"skuMultiCurrencyDisplayPrice\":\"32.46\"}},{\"skuAttr\":\"14:200005536;200007763:201336103\",\"skuPropIds\":\"200005536,201336103\",\"skuVal\":{\"availQuantity\":0,\"inventory\":0,\"isActivity\":false,\"skuCalPrice\":\"32.46\",\"skuMultiCurrencyCalPrice\":\"32.46\",\"skuMultiCurrencyDisplayPrice\":\"32.46\"}},{\"skuAttr\":\"14:10;200007763:201336100\",\"skuPropIds\":\"10,201336100\",\"skuVal\":{\"availQuantity\":953,\"inventory\":999,\"isActivity\":false,\"skuCalPrice\":\"32.46\",\"skuMultiCurrencyCalPrice\":\"32.46\",\"skuMultiCurrencyDisplayPrice\":\"32.46\"}},{\"skuAttr\":\"14:10;200007763:201336103\",\"skuPropIds\":\"10,201336103\",\"skuVal\":{\"availQuantity\":28,\"inventory\":43,\"isActivity\":false,\"skuCalPrice\":\"32.46\",\"skuMultiCurrencyCalPrice\":\"32.46\",\"skuMultiCurrencyDisplayPrice\":\"32.46\"}},{\"skuAttr\":\"14:366;200007763:201336100\",\"skuPropIds\":\"366,201336100\",\"skuVal\":{\"availQuantity\":990,\"inventory\":999,\"isActivity\":false,\"skuCalPrice\":\"32.46\",\"skuMultiCurrencyCalPrice\":\"32.46\",\"skuMultiCurrencyDisplayPrice\":\"32.46\"}},{\"skuAttr\":\"14:366;200007763:201336103\",\"skuPropIds\":\"366,201336103\",\"skuVal\":{\"availQuantity\":0,\"inventory\":0,\"isActivity\":false,\"skuCalPrice\":\"32.46\",\"skuMultiCurrencyCalPrice\":\"32.46\",\"skuMultiCurrencyDisplayPrice\":\"32.46\"}}];\n\t        var GaData = {\n        pageType: \"product\",\n        productIds: \"en1904533610\",\n        totalValue: \"US $32.46\"\n    };\n\n\t\t    window.runParams.isFixedFreeShipping=false;\n\twindow.runParams.fixedFreeShippingTip='';\n\twindow.runParams.bigSaleIconUrl='';\n\twindow.runParams.rmStoreLevelAB = \"true\";\n    "
        ],
        "Type": [
            "Knives"
        ]
    }
]