[
    {
        "Certification": [
            "Birch &amp; German food grade Ink"
        ],
        "Feature": [
            "Other Festive &amp; Party Supplies"
        ],
        "Knife Type": [
            "New Year"
        ],
        "Material": [
            "wooden cutlery"
        ],
        "Model Number": [
            "wu01-90"
        ],
        "Name": [
            "Promotion!!! Colorful Polka dot  Wooden Knife Party Supplies Wooden Cutlery Set Free Shipping"
        ],
        "Type": [
            "Event &amp; Party Supplies"
        ]
    }
]