[
    {
        "Brand": [
            "Mercer Cutlery"
        ],
        "Color": [
            "Steel, Brown"
        ],
        "Country": [
            "Lifetime Limited Manufacturer Warranty"
        ],
        "Material": [
            "Plastic and Steel"
        ],
        "Name": [
            "Mercer Hell's Handles Grill Spatula - Heat Resistant 14.25\" Perforated"
        ],
        "Options": [
            "Home"
        ],
        "Price": [
            "Pin This"
        ],
        "SKU": [
            "\n\t\t\t\t\tItem #: M18310\t\t\t\t"
        ],
        "Type": [
            "Turners"
        ]
    }
]